pythia_client/__init__.py
pythia_client/client.py
pythia_client/schema.py
pythia_client/utils.py
pythia_client/analytics/__init__.py
pythia_client/analytics/conversations.py
pythia_client/analytics/feedback.py
pythia_client/analytics/metrics.py
pythia_client/auth/__init__.py
pythia_client/auth/api_keys.py
pythia_client/chunks/__init__.py
pythia_client/chunks/facets.py
pythia_client/chunks/filter.py
pythia_client/chunks/metadata.py
pythia_client/chunks/retrieval.py
pythia_client/files/__init__.py
pythia_client/files/files_info.py
pythia_client/files/indexing.py
pythia_client/pipelines/__init__.py
pythia_client/pipelines/pipelines.py
pythia_client/query/__init__.py
pythia_client/query/agent.py
pythia_client/query/chat.py
pythia_client/query/rag.py
pythia_client/query/retrieve.py
pythia_client/schema/__init__.py
pythia_client/schema/auth.py
pythia_client/schema/base.py
pythia_client/schema/chunks.py
pythia_client/schema/conversation.py
pythia_client/schema/feedback.py
pythia_client/schema/files.py
pythia_client/schema/indexing.py
pythia_client/schema/query.py
pythia_client/schema/structured_data.py
pythia_client/structured_data/__init__.py
pythia_client/structured_data/structured_data.py
pythia_client/utils/__init__.py
pythia_client/utils/base.py
pythia_client/utils/http.py
pythia_client/utils/streaming.py
pythia_client-0.20.0.dist-info/METADATA
pythia_client-0.20.0.dist-info/WHEEL
pythia_client-0.20.0.dist-info/licenses/LICENSE
pythia_client-0.20.0.dist-info/RECORD
