Metadata-Version: 2.4
Name: pythia-client
Version: 0.20.0
Summary: Client to interact with the Pythia API
Project-URL: Homepage, https://gitlab.com/ale-gitlab/dto/data-science/cip-bot/project-pythia
Project-URL: Documentation, https://gitlab.com/ale-gitlab/dto/data-science/cip-bot/project-pythia
Project-URL: Repository, https://gitlab.com/ale-gitlab/dto/data-science/cip-bot/project-pythia
Project-URL: Issues, https://gitlab.com/ale-gitlab/dto/data-science/cip-bot/project-pythia/-/issues
Author-email: Corentin Meyer <contact@cmeyer.fr>
Maintainer-email: Corentin Meyer <contact@cmeyer.fr>
License: Apache 2.0
License-File: LICENSE
Classifier: Development Status :: 3 - Alpha
Classifier: Intended Audience :: Developers
Classifier: Programming Language :: Python
Classifier: Programming Language :: Python :: 3.8
Classifier: Programming Language :: Python :: 3.9
Classifier: Programming Language :: Python :: 3.10
Classifier: Programming Language :: Python :: 3.11
Classifier: Programming Language :: Python :: 3.12
Requires-Python: >=3.10
Requires-Dist: pydantic>=2.6.4
Requires-Dist: requests>=2.31.0
